ipscap/__init__.py
ipscap/__main__.py
ipscap/configs.py
ipscap/ipscap_cmd.py
ipscap/core/__init__.py
ipscap/core/object_factory.py
ipscap/core/pipeline.py
ipscap/service/__init__.py
ipscap/service/args_builder.py
ipscap/service/dumpfile.py
ipscap/service/eth_socket.py
ipscap/service/packet_filter.py
ipscap/service/protocol_service.py
ipscap/service/transfer_store.py
ipscap/service/view_helper.py
ipscap/util/__init__.py
ipscap/util/evaluation_parser.py
ipscap/util/raw_socket_entity.py
ipscap/util/raw_socket_parser.py
ipsend/__init__.py
ipsend/__main__.py
ipsend/configs.py
ipsend/ipsend_cmd.py
ipsend/core/__init__.py
ipsend/core/object_factory.py
ipsend/core/pipeline.py
ipsend/service/__init__.py
ipsend/service/args_builder.py
ipsend/service/dumpfile.py
ipsend/service/packet_generator.py
ipsend/service/sockets.py
ipsend/service/view_helper.py
ipsend/util/__init__.py
ipsend/util/data_io.py
ipsend/util/raw_socket_entity.py
ipsend/util/raw_socket_generator.py
ipsurv/__init__.py
ipsurv/__main__.py
ipsurv/configs.py
ipsurv/ip_surv_cmd.py
ipsurv/survey_ips.py
ipsurv/survey_self.py
ipsurv/configure/__init__.py
ipsurv/configure/args_builder.py
ipsurv/configure/args_validators.py
ipsurv/core/__init__.py
ipsurv/core/entity.py
ipsurv/core/object_factory.py
ipsurv/core/pipeline.py
ipsurv/core/target_groups.py
ipsurv/core/target_parser.py
ipsurv/data_collector/__init__.py
ipsurv/data_collector/basic_collectors.py
ipsurv/data_collector/data_collector.py
ipsurv/data_collector/geoip_collector.py
ipsurv/data_collector/pass_data_collector.py
ipsurv/data_collector/reactivity_collectors.py
ipsurv/data_collector/self_collector.py
ipsurv/requester/__init__.py
ipsurv/requester/dns_resolver.py
ipsurv/requester/geoip.py
ipsurv/requester/http.py
ipsurv/requester/ip_info.py
ipsurv/requester/rdap.py
ipsurv/requester/requester.py
ipsurv/requester/server_reactivity.py
ipsurv/serializer/__init__.py
ipsurv/serializer/json_serializer.py
ipsurv/serializer/line_serializer.py
ipsurv-1.3.2.dist-info/licenses/LICENSE.md
ipsurv-1.3.2.dist-info/METADATA
ipsurv-1.3.2.dist-info/WHEEL
ipsurv-1.3.2.dist-info/entry_points.txt
ipsurv-1.3.2.dist-info/top_level.txt
ipsurv-1.3.2.dist-info/RECORD
