Metadata-Version: 2.4
Name: ipsurv
Version: 1.3.2
Summary: "IpSurv" are investigation tools for surveying IP addresses, network investigation, test and debugging - "ipsurv, ipscap, ipsend". Those tools allow for packet capture, such as tcpdump, and packet sending tests. Each tools and internal program are extensible using Python.
Home-page: https://github.com/deer-hunt/ipsurv
Author: deer-hunt
License: MIT
Project-URL: Documentation, https://deer-hunt.github.io/ipsurv/
Project-URL: Github, https://github.com/deer-hunt/ipsurv/
Project-URL: Changelog, https://github.com/deer-hunt/ipsurv/blob/main/CHANGELOG.md
Keywords: ip,tcpdump,capture,packet,network,rdap,whois,http,tcp,udp,header,ipscap,ipsend,ipserver,debug,test
Classifier: Development Status :: 5 - Production/Stable
Classifier: Intended Audience :: Developers
Classifier: Intended Audience :: System Administrators
Classifier: Intended Audience :: Information Technology
Classifier: Intended Audience :: Science/Research
Classifier: Intended Audience :: Telecommunications Industry
Classifier: Programming Language :: Python :: 3
Classifier: Programming Language :: Python :: 3.6
Classifier: Programming Language :: Python :: 3.7
Classifier: Programming Language :: Python :: 3.8
Classifier: Programming Language :: Python :: 3.9
Classifier: Programming Language :: Python :: 3.10
Classifier: Programming Language :: Python :: 3.11
Classifier: Programming Language :: Python :: 3.12
Classifier: Programming Language :: Python :: 3.13
Classifier: License :: OSI Approved :: MIT License
Classifier: Operating System :: OS Independent
Classifier: Topic :: Software Development :: Libraries :: Python Modules
Requires-Python: >=3.0
License-File: LICENSE.md
Requires-Dist: pip
Requires-Dist: dnspython
Dynamic: license-file
